atomacos/AXCallbacks.py
atomacos/AXClasses.py
atomacos/__init__.py
atomacos/_a11y.py
atomacos/_converter.py
atomacos/_macos.py
atomacos/_notification.py
atomacos/errors.py
atomacos/keyboard.py
atomacos/mouse.py
atomacos/_mixin/__init__.py
atomacos/_mixin/_input.py
atomacos/_mixin/_search.py
atomacos/_mixin/_wait.py
atomacos-3.3.0.dist-info/LICENSE
atomacos-3.3.0.dist-info/WHEEL
atomacos-3.3.0.dist-info/METADATA
atomacos-3.3.0.dist-info/RECORD
