Metadata-Version: 2.1
Name: atomacos
Version: 3.3.0
Summary: Automated Testing on macOS
Home-page: https://github.com/daveenguyen/atomacos
License: UNKNOWN
Author: Davee Nguyen
Author-email: davee@daveenguyen.com
Classifier: Development Status :: 5 - Production/Stable
Classifier: Environment :: MacOS X
Classifier: Environment :: MacOS X :: Cocoa
Classifier: Intended Audience :: Developers
Classifier: License :: OSI Approved :: GNU General Public License v2 (GPLv2)
Classifier: Operating System :: MacOS
Classifier: Operating System :: MacOS :: MacOS X
Classifier: Programming Language :: Objective C
Classifier: Programming Language :: Python
Classifier: Programming Language :: Python :: 2.7
Classifier: Programming Language :: Python :: 3
Classifier: Programming Language :: Python :: 3.4
Classifier: Programming Language :: Python :: 3.5
Classifier: Programming Language :: Python :: 3.6
Classifier: Programming Language :: Python :: 3.7
Classifier: Topic :: Software Development :: Libraries
Classifier: Topic :: Software Development :: Libraries :: Python Modules
Classifier: Topic :: Software Development :: Quality Assurance
Classifier: Topic :: Software Development :: Testing
Classifier: Topic :: Software Development :: User Interfaces
Requires-Dist: pyobjc-core>=3.0.4
Requires-Dist: pyobjc-framework-Cocoa>=3.0.4
Requires-Dist: pyobjc-framework-Quartz>=3.0.4
Requires-Dist: pyobjc-framework-ApplicationServices>=3.0.4
Requires-Dist: pyobjc-framework-CoreText>=3.0.4
Requires-Dist: pygetwindow<0.0.5
Requires-Dist: pyscreeze<0.1.20
Requires-Dist: pyautogui<0.9.42
Requires-Dist: future
Requires-Dist: black ; extra == "dev"
Requires-Dist: pre-commit ; extra == "dev"
Requires-Dist: tox ; extra == "dev"
Requires-Dist: sphinx ; extra == "doc"
Requires-Dist: m2r2 ; extra == "doc"
Requires-Dist: pytest ; extra == "test"
Requires-Dist: pytest-cov ; extra == "test"
Provides-Extra: dev
Provides-Extra: doc
Provides-Extra: test
